kaera/__main__.py
kaera/default.py
kaera/gitlab_handler.py
kaera/population.py
kaera/project.py
Kaera-1.0.6.dist-info/LICENSE
Kaera-1.0.6.dist-info/METADATA
Kaera-1.0.6.dist-info/WHEEL
Kaera-1.0.6.dist-info/entry_points.txt
Kaera-1.0.6.dist-info/top_level.txt
Kaera-1.0.6.dist-info/RECORD
