Metadata-Version: 2.1
Name: Kaera
Version: 1.0.6
Summary: Project initiator
Home-page: UNKNOWN
Author: Emmanuel PLUOT
License: MIT
Platform: linux
Classifier: Programming Language :: Python :: 3 :: Only
Classifier: Programming Language :: Python :: 3.9
Requires-Python: >=3.8
License-File: LICENSE
Requires-Dist: GitPython (>=3.1.24)
Requires-Dist: python-gitlab (>=3.10.0)
Requires-Dist: sonotoria (>=0.3.7)
Provides-Extra: testing
Requires-Dist: pytest-cov (>=2.0) ; extra == 'testing'
Requires-Dist: pytest (>=6.0) ; extra == 'testing'
